req2toml/__init__.py
req2toml/console.py
req2toml/utils.py
req2toml-1.2.0.dist-info/entry_points.txt
req2toml-1.2.0.dist-info/LICENSE
req2toml-1.2.0.dist-info/WHEEL
req2toml-1.2.0.dist-info/METADATA
req2toml-1.2.0.dist-info/RECORD
