Metadata-Version: 2.1
Name: req2toml
Version: 1.2.0
Summary: Convert requirements.txt to pyproject.toml
Home-page: https://github.com/benbenbang/req2toml
License: Apache-2.0
Keywords: poetry,pyproject,toml,requirements,convert
Author: Ben Chen
Author-email: benbenbang@github.com
Requires-Python: >=3.6.1,<4.0.0
Classifier: Development Status :: 5 - Production/Stable
Classifier: Intended Audience :: Developers
Classifier: Intended Audience :: Science/Research
Classifier: License :: OSI Approved :: Apache Software License
Classifier: Programming Language :: Python :: 3
Classifier: Programming Language :: Python :: 3.6
Classifier: Programming Language :: Python :: 3.7
Classifier: Programming Language :: Python :: 3.8
Classifier: Programming Language :: Python :: 3.9
Requires-Dist: click (==7.1.2)
Project-URL: Repository, https://github.com/benbenbang/req2toml
